pyvectorize/__init__.py
pyvectorize/api_client.py
pyvectorize/api_response.py
pyvectorize/configuration.py
pyvectorize/exceptions.py
pyvectorize/py.typed
pyvectorize/rest.py
pyvectorize/api/__init__.py
pyvectorize/api/default_api.py
pyvectorize/models/__init__.py
pyvectorize/models/index_query_request_schema.py
pyvectorize/models/index_upsert_request_schema.py
pyvectorize/models/index_upsert_request_schema_id.py
pyvectorize/models/indexes_get200_response.py
pyvectorize/models/indexes_get200_response_id.py
pyvectorize/models/indexes_info_get200_response.py
pyvectorize/models/indexes_info_get200_response_result.py
pyvectorize/models/indexes_info_get200_response_result_config.py
pyvectorize/models/indexes_info_get200_response_result_config_hnsw_config.py
pyvectorize/models/indexes_info_get200_response_result_config_optimizer_config.py
pyvectorize/models/indexes_info_get200_response_result_config_params.py
pyvectorize/models/indexes_info_get200_response_result_config_params_vectors_value.py
pyvectorize/models/indexes_info_get200_response_result_config_wal_config.py
pyvectorize/models/indexes_query_post200_response.py
pyvectorize/models/indexes_query_post200_response_result_inner.py
pyvectorize/models/indexes_upsert_post200_response.py
pyvectorize/models/indexes_upsert_post200_response_inserted.py
pyvectorize-0.1.1.dist-info/METADATA
pyvectorize-0.1.1.dist-info/WHEEL
pyvectorize-0.1.1.dist-info/top_level.txt
pyvectorize-0.1.1.dist-info/RECORD
