Metadata-Version: 2.1
Name: pyvectorize
Version: 0.1.1
Summary: vectorize.sh API
Home-page: https://vectorize.sh
Author: OpenAPI Generator community
Author-email: team@openapitools.org
Keywords: OpenAPI,OpenAPI-Generator,vectorize.sh API
Requires-Dist: urllib3 (<2.1.0,>=1.25.3)
Requires-Dist: python-dateutil
Requires-Dist: pydantic (>=2)
Requires-Dist: typing-extensions (>=4.7.1)
